liblzfse.cpython-39-darwin.so
pyliblzfse-0.4.1.dist-info/AUTHORS
pyliblzfse-0.4.1.dist-info/COPYING
pyliblzfse-0.4.1.dist-info/LICENSE.lzfse
pyliblzfse-0.4.1.dist-info/METADATA
pyliblzfse-0.4.1.dist-info/WHEEL
pyliblzfse-0.4.1.dist-info/top_level.txt
pyliblzfse-0.4.1.dist-info/RECORD
