Metadata-Version: 2.1
Name: pyliblzfse
Version: 0.4.1
Summary: Python bindings for the LZFSE reference implementation
Home-page: https://github.com/ydkhatri/pyliblzfse
Author: Yogesh Khatri
Author-email: yogesh@swiftforensics.com
License: MIT
Platform: UNKNOWN
